ofxstatement_be_belfius-0.0.2-py3.7-nspkg.pth
ofxstatement/plugins/belfius.py
ofxstatement_be_belfius-0.0.2.dist-info/LICENSE
ofxstatement_be_belfius-0.0.2.dist-info/METADATA
ofxstatement_be_belfius-0.0.2.dist-info/WHEEL
ofxstatement_be_belfius-0.0.2.dist-info/entry_points.txt
ofxstatement_be_belfius-0.0.2.dist-info/namespace_packages.txt
ofxstatement_be_belfius-0.0.2.dist-info/top_level.txt
ofxstatement_be_belfius-0.0.2.dist-info/zip-safe
ofxstatement_be_belfius-0.0.2.dist-info/RECORD
