Metadata-Version: 2.1
Name: ofxstatement-be-belfius
Version: 0.0.2
Summary: Belfius bank plugin for ofxstatement (Belgium)
Home-page: https://github.com/renardeau/ofxstatement-be-belfius.git
Author: Bernard Butaye
Author-email: UNKNOWN
License: UNKNOWN
Keywords: ofx,banking,statement
Platform: UNKNOWN
Classifier: Development Status :: 3 - Alpha
Classifier: Programming Language :: Python :: 3
Classifier: Natural Language :: English
Classifier: Topic :: Office/Business :: Financial :: Accounting
Classifier: Topic :: Utilities
Classifier: Environment :: Console
Classifier: Operating System :: OS Independent
Classifier: License :: OSI Approved :: GNU General Public License v3 (GPLv3)
Requires-Dist: ofxstatement
